{
    "contests": [{
        "id": "contest_demo_001",
        "title": "我眼中的抗战精神",
        "description": "用文字或图画描绘你对抗战精神的理解,展现不屈不挠、团结一心、视死如归的民族精神在当代的传承与发扬。",
        "category": "文章+图片",
        "startDate": "2025-01-01",
        "endDate": "2025-01-31",
        "status": "ongoing",
        "rules": "作品要求:\n1. 原创作品,积极向上\n2. 文章字数1000-3000字\n3. 图片作品需配简要说明(200字以上)\n4. 禁止抄袭,一经发现取消参赛资格",
        "prize": "一等奖1名:荣誉证书+纪念品\n二等奖3名:荣誉证书\n三等奖5名:优秀奖证书\n所有参与者获得'创作之星'电子徽章",
        "createdBy": "佟雨泽",
        "createdAt": "2024-12-25T10:00:00.000Z",
        "submissionCount": 0
    }]
}